sheetslib/__init__.py
sheetslib/sheetslib.py
sheetslib-0.2.2.dist-info/LICENSE
sheetslib-0.2.2.dist-info/METADATA
sheetslib-0.2.2.dist-info/WHEEL
sheetslib-0.2.2.dist-info/top_level.txt
sheetslib-0.2.2.dist-info/RECORD
