Metadata-Version: 2.1
Name: sheetslib
Version: 0.2.2
Summary: An object-oriented add-on for the gspread library
Home-page: https://github.com/caseyjohnsonwv/sheetslib
Author: Casey Johnson
Author-email: ctj0001@mix.wvu.edu
License: UNKNOWN
Platform: UNKNOWN
Classifier: Programming Language :: Python :: 3
Classifier: License :: OSI Approved :: MIT License
Classifier: Operating System :: OS Independent
Requires-Dist: gspread
